fastdup/__init__.py
fastdup-2.50.dist-info/METADATA
fastdup-2.50.dist-info/WHEEL
fastdup-2.50.dist-info/top_level.txt
fastdup-2.50.dist-info/RECORD
