Metadata-Version: 2.1
Name: fastdup
Version: 2.50
Summary: FastDup Python 3.7/3.8 compatibility stub - shows version requirement error
Home-page: https://github.com/visualdatabase/fastdup
Author: Dr. Danny Bickson & Dr. Amir Alush
Author-email: info@visual-layer.com
License: Non commercial
Keywords: computer-vision,image-analytics,video-analytics,image-processing
Classifier: Development Status :: 5 - Production/Stable
Classifier: Intended Audience :: Developers
Classifier: License :: Other/Proprietary License
Classifier: Programming Language :: Python :: 3.7
Classifier: Programming Language :: Python :: 3.8
Classifier: Topic :: Scientific/Engineering :: Image Processing
Classifier: Topic :: Multimedia :: Video
Classifier: Topic :: Software Development :: Libraries :: Python Modules
Requires-Python: >=3.7,<3.9
Requires-Dist: sentry-sdk (>=1.0.0)
